setup.py
boxmongodb/__init__.py
boxmongodb/boxmongodb.py
boxmongodb.egg-info/PKG-INFO
boxmongodb.egg-info/SOURCES.txt
boxmongodb.egg-info/dependency_links.txt
boxmongodb.egg-info/requires.txt
boxmongodb.egg-info/top_level.txt