Metadata-Version: 1.0
Name: boxmongodb
Version: 0.0.10
Summary: just a simple mongodb orm
Home-page: UNKNOWN
Author: CcdjhMarx
Author-email: ccdjh.marx@all.com
License: MIT License
Keywords: mongodb,db
Platform: UNKNOWN
